{
	"range": ["2010-10","2020-03"],
	"data": {
	"34500": {
		"name": "Paypal *justinhanco",
		"total": 27.17,
		"monthly": {
			"2015-10": {"total":16.67, "Childrens Services":16.67},
			"2017-08": {"total":10.50, "Adults and Health":10.50}
		}
	},
	"34501": {
		"name": "Paypal *justinjayli",
		"total": 21.54,
		"monthly": {
			"2016-04": {"total":21.54, "Environment & Housing":21.54}
		}
	},
	"34502": {
		"name": "Paypal *jw Tools Ebay",
		"total": 12.04,
		"monthly": {
			"2020-01": {"total":12.04, "Resources and Housing":12.04}
		}
	},
	"34503": {
		"name": "Paypal *kaizenprint",
		"total": 330,
		"monthly": {
			"2019-09": {"total":330.00, "Communities and Environment":330.00}
		}
	},
	"34504": {
		"name": "Paypal *kaleco Sign",
		"total": 29.96,
		"monthly": {
			"2016-10": {"total":29.96, "City Development":29.96}
		}
	},
	"34505": {
		"name": "Paypal *kamsat Ltd",
		"total": 6.99,
		"monthly": {
			"2017-12": {"total":6.99, "Communities and Environment":6.99}
		}
	},
	"34506": {
		"name": "Paypal *kavelightin",
		"total": 10,
		"monthly": {
			"2016-11": {"total":10.00, "City Development":10.00}
		}
	},
	"34507": {
		"name": "Paypal *kbstrading",
		"total": 149.1,
		"monthly": {
			"2016-07": {"total":149.10, "Childrens Services":149.10}
		}
	},
	"34508": {
		"name": "Paypal *keepbritain",
		"total": 58.33,
		"monthly": {
			"2015-04": {"total":33.33, "Environment & Housing":33.33},
			"2015-07": {"total":25.00, "Environment & Housing":25.00}
		}
	},
	"34509": {
		"name": "Paypal *kenable Ltd",
		"total": 124.78,
		"monthly": {
			"2016-05": {"total":104.50, "City Development":104.50},
			"2019-10": {"total":20.28, "Communities and Environment":20.28}
		}
	},
	"34510": {
		"name": "Paypal *kenjan57",
		"total": 28.9,
		"monthly": {
			"2017-11": {"total":28.90, "City Development":28.90}
		}
	},
	"34511": {
		"name": "Paypal *kennethbrad",
		"total": 10.83,
		"monthly": {
			"2018-01": {"total":10.83, "Strategic Landlord":10.83}
		}
	},
	"34512": {
		"name": "Paypal *kieranh Des",
		"total": 17,
		"monthly": {
			"2016-04": {"total":17.00, "City Development":17.00}
		}
	},
	"34513": {
		"name": "Paypal *kingdomfanc",
		"total": 40.31,
		"monthly": {
			"2018-01": {"total":14.93, "Children and Families":14.93},
			"2018-10": {"total":25.38, "City Development":25.38}
		}
	},
	"34514": {
		"name": "Paypal *kingsfieldc",
		"total": 1614.4,
		"monthly": {
			"2015-04": {"total":1614.40, "Central & Corporate":1614.40}
		}
	},
	"34515": {
		"name": "Paypal *klickklickl",
		"total": 4.78,
		"monthly": {
			"2017-09": {"total":4.78, "Communities and Environment":4.78}
		}
	},
	"34516": {
		"name": "Paypal *klicnow Ltd",
		"total": 108.3,
		"monthly": {
			"2017-06": {"total":108.30, "City Development":108.30}
		}
	},
	"34517": {
		"name": "Paypal *kolinkelly",
		"total": 2.99,
		"monthly": {
			"2019-09": {"total":2.99, "Communities and Environment":2.99}
		}
	},
	"34518": {
		"name": "Paypal *kootchypro",
		"total": 41.66,
		"monthly": {
			"2019-02": {"total":41.66, "Children and Families":41.66}
		}
	},
	"34519": {
		"name": "Paypal *krystalleba",
		"total": 3.99,
		"monthly": {
			"2019-09": {"total":3.99, "Communities and Environment":3.99}
		}
	},
	"34520": {
		"name": "Paypal *kudliansoft",
		"total": 16.66,
		"monthly": {
			"2019-04": {"total":16.66, "City Development":16.66}
		}
	},
	"34521": {
		"name": "Paypal *kwik2mecove",
		"total": 93.71,
		"monthly": {
			"2015-11": {"total":93.71, "City Development":93.71}
		}
	},
	"34522": {
		"name": "Paypal *kyzenmedia",
		"total": 80.82,
		"monthly": {
			"2017-08": {"total":80.82, "City Development":80.82}
		}
	},
	"34523": {
		"name": "Paypal *l Tactical",
		"total": 179.36,
		"monthly": {
			"2015-06": {"total":179.36, "Central & Corporate":179.36}
		}
	},
	"34524": {
		"name": "Paypal *labelrlimit",
		"total": 18.89,
		"monthly": {
			"2018-02": {"total":18.89, "Children and Families":18.89}
		}
	},
	"34525": {
		"name": "Paypal *lag",
		"total": 117,
		"monthly": {
			"2019-08": {"total":53.50, "Resources and Housing":53.50},
			"2019-09": {"total":63.50, "Communities and Environment":63.50}
		}
	},
	"34526": {
		"name": "Paypal *lalchris",
		"total": 41.28,
		"monthly": {
			"2015-06": {"total":41.28, "Childrens Services":41.28}
		}
	},
	"34527": {
		"name": "Paypal *landabooks",
		"total": 11.62,
		"monthly": {
			"2015-11": {"total":11.62, "City Development":11.62}
		}
	},
	"34528": {
		"name": "Paypal *landscapein",
		"total": 1234.64,
		"monthly": {
			"2015-07": {"total":258.33, "Environment & Housing":258.33},
			"2016-02": {"total":717.07, "Environment & Housing":717.07},
			"2016-10": {"total":259.24, "Environment & Housing":259.24}
		}
	},
	"34529": {
		"name": "Paypal *laptone Ltd",
		"total": 6.99,
		"monthly": {
			"2016-03": {"total":6.99, "Civic Enterprise Leeds":6.99}
		}
	},
	"34530": {
		"name": "Paypal *laptoppower",
		"total": 41.66,
		"monthly": {
			"2017-02": {"total":41.66, "Civic Enterprise Leeds":41.66}
		}
	},
	"34531": {
		"name": "Paypal *latekaslavi",
		"total": 2.19,
		"monthly": {
			"2017-05": {"total":2.19, "Children and Families":2.19}
		}
	},
	"34532": {
		"name": "Paypal *lauhanlimit",
		"total": 24.99,
		"monthly": {
			"2017-02": {"total":24.99, "City Development":24.99}
		}
	},
	"34533": {
		"name": "Paypal *leadershipt",
		"total": 388.13,
		"monthly": {
			"2019-11": {"total":388.13, "Resources and Housing":388.13}
		}
	},
	"34534": {
		"name": "Paypal *leeds Mind",
		"total": 2340,
		"monthly": {
			"2016-06": {"total":300.00, "Central & Corporate":150.00, "Public Health":150.00},
			"2018-04": {"total":255.00, "Resources and Housing":255.00},
			"2018-05": {"total":1020.00, "Communities and Environment":510.00, "Resources and Housing":510.00},
			"2018-06": {"total":765.00, "Resources and Housing":765.00}
		}
	},
	"34535": {
		"name": "Paypal *leedscamps",
		"total": 50.5,
		"monthly": {
			"2019-07": {"total":50.50, "Children and Families":50.50}
		}
	},
	"34536": {
		"name": "Paypal *leedschurch",
		"total": 18,
		"monthly": {
			"2017-01": {"total":18.00, "Citizens and Communities":18.00}
		}
	},
	"34537": {
		"name": "Paypal *leedsmuseum",
		"total": 30,
		"monthly": {
			"2019-05": {"total":30.00, "City Development":30.00}
		}
	},
	"34538": {
		"name": "Paypal *leedsprintc",
		"total": 274.66,
		"monthly": {
			"2015-09": {"total":78.33, "City Development":78.33},
			"2015-10": {"total":60.00, "City Development":60.00},
			"2015-11": {"total":35.00, "City Development":35.00},
			"2016-10": {"total":68.00, "City Development":68.00},
			"2016-11": {"total":33.33, "City Development":33.33}
		}
	},
	"34539": {
		"name": "Paypal *leesruth",
		"total": 4.99,
		"monthly": {
			"2016-07": {"total":4.99, "Childrens Services":4.99}
		}
	},
	"34540": {
		"name": "Paypal *legsgalorel",
		"total": 102.95,
		"monthly": {
			"2017-02": {"total":3.50, "City Development":3.50},
			"2017-05": {"total":33.00, "Environment & Housing":33.00},
			"2017-08": {"total":2.75, "Children and Families":2.75},
			"2018-06": {"total":29.50, "Communities and Environment":29.50},
			"2019-07": {"total":34.20, "Communities and Environment":34.20}
		}
	},
	"34541": {
		"name": "Paypal *leisuremedi",
		"total": 181.33,
		"monthly": {
			"2015-07": {"total":53.33, "City Development":53.33},
			"2019-04": {"total":128.00, "City Development":128.00}
		}
	},
	"34542": {
		"name": "Paypal *leisurewear",
		"total": 7.49,
		"monthly": {
			"2018-06": {"total":7.49, "City Development":7.49}
		}
	},
	"34543": {
		"name": "Paypal *lennoxtradi",
		"total": 98,
		"monthly": {
			"2018-02": {"total":98.00, "City Development":98.00}
		}
	},
	"34544": {
		"name": "Paypal *lensadapt4u",
		"total": 366,
		"monthly": {
			"2016-03": {"total":366.00, "Childrens Services":366.00}
		}
	},
	"34545": {
		"name": "Paypal *leomay Ltd Eba",
		"total": 23.24,
		"monthly": {
			"2020-02": {"total":23.24, "City Development":23.24}
		}
	},
	"34546": {
		"name": "Paypal *lgcomms",
		"total": 4420,
		"monthly": {
			"2016-10": {"total":1398.00, "Central & Corporate":1398.00},
			"2017-04": {"total":250.00, "Resources and Housing":250.00},
			"2017-06": {"total":1980.00, "Resources and Housing":1980.00},
			"2017-07": {"total":792.00, "Resources and Housing":792.00}
		}
	},
	"34547": {
		"name": "Paypal *lgcomms2018",
		"total": 430,
		"monthly": {
			"2019-08": {"total":180.00, "Children and Families":180.00},
			"2019-09": {"total":250.00, "Adults and Health":250.00}
		}
	},
	"34548": {
		"name": "Paypal *li Gaoqin",
		"total": 32.5,
		"monthly": {
			"2019-02": {"total":32.50, "Children and Families":32.50}
		}
	},
	"34549": {
		"name": "Paypal *li Huifang",
		"total": 8.8,
		"monthly": {
			"2017-09": {"total":8.80, "Communities and Environment":8.80}
		}
	}
	}
}