{
	"range": ["2010-10","2022-08"],
	"data": {
	"4300": {
		"name": "Artist Management",
		"total": 252.2,
		"monthly": {
			"2016-03": {"total":252.20, "Childrens Services":252.20}
		}
	},
	"4301": {
		"name": "Artist Needs Ltd",
		"total": 4064.6,
		"monthly": {
			"2011-04": {"total":564.60, "City Development":564.60},
			"2021-05": {"total":1000.00, "City Development":1000.00},
			"2021-06": {"total":500.00, "City Development":500.00},
			"2021-08": {"total":2000.00, "City Development":2000.00}
		}
	},
	"4302": {
		"name": "Artistic Crew Tattoo Studios",
		"total": 906.72,
		"monthly": {
			"2016-03": {"total":906.72, "City Development":906.72}
		}
	},
	"4303": {
		"name": "Artistic Solutions Ltd",
		"total": 5707.5,
		"monthly": {
			"2017-10": {"total":5707.50, "City Development":5707.50}
		}
	},
	"4304": {
		"name": "Artlink West Yorkshire",
		"total": 133582.5,
		"monthly": {
			"2011-04": {"total":2235.50, "Adult Social Care":2235.50},
			"2011-05": {"total":14902.00, "City Development":14902.00},
			"2011-12": {"total":2395.10, "Environment & Neighbourhoods":2395.10},
			"2012-01": {"total":1324.10, "Environment & Neighbourhoods":1324.10},
			"2012-02": {"total":1411.55, "Environment & Neighbourhoods":1411.55},
			"2012-03": {"total":1454.77, "Environment & Neighbourhoods":1454.77},
			"2012-04": {"total":1314.48, "Environment & Neighbourhoods":1314.48},
			"2012-05": {"total":12000.00, "City Development":12000.00},
			"2013-04": {"total":12000.00, "City Development":12000.00},
			"2014-03": {"total":1000.00, "City Development":1000.00},
			"2014-04": {"total":12000.00, "City Development":12000.00},
			"2014-06": {"total":5000.00, "Adult Social Care":5000.00},
			"2015-05": {"total":9600.00, "City Development":9600.00},
			"2016-04": {"total":8208.00, "City Development":8208.00},
			"2016-05": {"total":912.00, "City Development":912.00},
			"2017-03": {"total":1000.00, "City Development":1000.00},
			"2017-04": {"total":8208.00, "City Development":8208.00},
			"2017-05": {"total":1000.00, "City Development":1000.00},
			"2017-06": {"total":912.00, "City Development":912.00},
			"2017-08": {"total":1000.00, "City Development":1000.00},
			"2017-11": {"total":1000.00, "City Development":1000.00},
			"2017-12": {"total":400.00, "City Development":400.00},
			"2018-05": {"total":8208.00, "City Development":8208.00},
			"2018-06": {"total":912.00, "City Development":912.00},
			"2019-04": {"total":8208.00, "City Development":8208.00},
			"2019-07": {"total":912.00, "City Development":912.00},
			"2019-12": {"total":7107.00, "Adults and Health":7107.00},
			"2020-04": {"total":8958.00, "City Development":8958.00}
		}
	},
	"4305": {
		"name": "Artloss.Com",
		"total": 130,
		"monthly": {
			"2016-08": {"total":60.00, "City Development":60.00},
			"2018-11": {"total":70.00, "City Development":70.00}
		}
	},
	"4306": {
		"name": "Artnumbers.Co.Uk",
		"total": 23.99,
		"monthly": {
			"2021-04": {"total":23.99, "Children and Families":23.99}
		}
	},
	"4307": {
		"name": "Artost Needs Ltd",
		"total": 1014,
		"monthly": {
			"2020-10": {"total":1014.00, "City Development":1014.00}
		}
	},
	"4308": {
		"name": "Artprice",
		"total": 655.44,
		"monthly": {
			"2016-07": {"total":45.80, "City Development":45.80},
			"2016-08": {"total":259.18, "City Development":259.18},
			"2017-06": {"total":156.68, "City Development":156.68},
			"2018-11": {"total":193.78, "City Development":193.78}
		}
	},
	"4309": {
		"name": "Artprice.Com",
		"total": 386.88,
		"monthly": {
			"2020-09": {"total":45.00, "City Development":45.00},
			"2021-10": {"total":165.02, "City Development":165.02},
			"2022-07": {"total":176.86, "City Development":176.86}
		}
	},
	"4310": {
		"name": "Arts & Flowers Ltd",
		"alternate-names": [
			"Arts & Flowers Limited"
		],
		"total": 130,
		"monthly": {
			"2018-06": {"total":130.00, "Children and Families":130.00}
		}
	},
	"4311": {
		"name": "Arts & Minds @ Inkwell",
		"total": 1000,
		"monthly": {
			"2020-08": {"total":1000.00, "Resources and Housing":1000.00}
		}
	},
	"4312": {
		"name": "Arts @ Trinity",
		"total": 2000,
		"monthly": {
			"2011-06": {"total":2000.00, "City Development":2000.00}
		}
	},
	"4313": {
		"name": "Arts @ Trinity Ltd",
		"total": 10606,
		"monthly": {
			"2014-02": {"total":150.00, "City Development":150.00},
			"2014-03": {"total":150.00, "City Development":150.00},
			"2014-05": {"total":150.00, "City Development":150.00},
			"2014-09": {"total":250.00, "City Development":250.00},
			"2014-11": {"total":250.00, "City Development":250.00},
			"2015-05": {"total":2000.00, "City Development":2000.00},
			"2015-09": {"total":250.00, "Strategic Accounts":250.00},
			"2015-10": {"total":96.00, "Strategic Accounts":96.00},
			"2016-02": {"total":950.00, "City Development":950.00},
			"2016-04": {"total":1900.00, "City Development":1900.00},
			"2016-05": {"total":300.00, "Childrens Services":250.00, "Strategic Accounts":50.00},
			"2016-06": {"total":100.00, "Strategic Accounts":100.00},
			"2016-07": {"total":300.00, "Strategic Accounts":300.00},
			"2017-04": {"total":2150.00, "Childrens Services":250.00, "City Development":1900.00},
			"2017-08": {"total":1300.00, "City Development":1300.00},
			"2017-12": {"total":60.00, "City Development":60.00},
			"2018-04": {"total":250.00, "Children and Families":250.00}
		}
	},
	"4314": {
		"name": "Arts And Flowers Ltd",
		"total": 12775.62,
		"monthly": {
			"2015-02": {"total":25.00, "Childrens Services":25.00},
			"2015-04": {"total":76.58, "Central & Corporate":25.00, "Childrens Services":51.58},
			"2015-05": {"total":146.90, "Childrens Services":146.90},
			"2015-06": {"total":350.00, "Childrens Services":350.00},
			"2015-07": {"total":200.00, "Childrens Services":200.00},
			"2015-08": {"total":25.00, "Childrens Services":25.00},
			"2015-09": {"total":76.58, "Childrens Services":76.58},
			"2015-10": {"total":154.16, "Childrens Services":154.16},
			"2015-11": {"total":175.00, "Childrens Services":175.00},
			"2015-12": {"total":101.63, "Childrens Services":101.63},
			"2016-01": {"total":164.90, "Childrens Services":164.90},
			"2016-02": {"total":142.49, "Childrens Services":142.49},
			"2016-03": {"total":151.67, "Childrens Services":151.67},
			"2016-04": {"total":180.00, "Childrens Services":180.00},
			"2016-05": {"total":385.82, "Childrens Services":385.82},
			"2016-06": {"total":811.83, "Childrens Services":811.83},
			"2016-07": {"total":315.00, "Childrens Services":315.00},
			"2016-08": {"total":105.00, "Childrens Services":105.00},
			"2016-09": {"total":185.00, "Childrens Services":185.00},
			"2016-10": {"total":165.00, "Childrens Services":165.00},
			"2016-11": {"total":250.83, "Childrens Services":250.83},
			"2016-12": {"total":90.00, "Childrens Services":90.00},
			"2017-01": {"total":131.90, "Childrens Services":131.90},
			"2017-02": {"total":200.83, "Childrens Services":200.83},
			"2017-03": {"total":105.00, "Childrens Services":105.00},
			"2017-04": {"total":50.00, "Children and Families":50.00},
			"2017-05": {"total":215.00, "Children and Families":215.00},
			"2017-06": {"total":170.00, "Children and Families":170.00},
			"2017-07": {"total":185.00, "Children and Families":185.00},
			"2017-08": {"total":385.00, "Children and Families":385.00},
			"2017-09": {"total":155.00, "Children and Families":155.00},
			"2017-10": {"total":281.67, "Adults and Health":26.67, "Children and Families":255.00},
			"2017-11": {"total":406.66, "Children and Families":406.66},
			"2017-12": {"total":246.66, "Adults and Health":20.00, "Children and Families":226.66},
			"2018-01": {"total":161.00, "Children and Families":161.00},
			"2018-02": {"total":125.00, "Children and Families":125.00},
			"2018-03": {"total":132.98, "Children and Families":132.98},
			"2018-04": {"total":125.00, "Children and Families":125.00},
			"2018-05": {"total":255.83, "Children and Families":255.83},
			"2018-06": {"total":255.75, "Children and Families":255.75},
			"2018-07": {"total":809.92, "Children and Families":809.92},
			"2018-08": {"total":368.00, "Children and Families":368.00},
			"2018-09": {"total":170.83, "Children and Families":170.83},
			"2018-10": {"total":305.00, "Children and Families":305.00},
			"2018-11": {"total":250.83, "Children and Families":250.83},
			"2018-12": {"total":68.33, "Children and Families":68.33},
			"2019-01": {"total":183.33, "Children and Families":183.33},
			"2019-02": {"total":125.00, "Children and Families":125.00},
			"2019-03": {"total":169.16, "Children and Families":169.16},
			"2019-05": {"total":391.33, "Children and Families":391.33},
			"2019-06": {"total":150.00, "Children and Families":150.00},
			"2019-07": {"total":151.66, "Children and Families":151.66},
			"2019-08": {"total":95.83, "Children and Families":95.83},
			"2019-09": {"total":151.66, "Children and Families":151.66},
			"2019-10": {"total":246.00, "Children and Families":246.00},
			"2019-11": {"total":540.00, "Children and Families":345.00, "City Development":50.00, "Resources and Housing":145.00},
			"2019-12": {"total":146.66, "Children and Families":146.66},
			"2020-01": {"total":150.83, "Children and Families":150.83},
			"2020-02": {"total":181.67, "Children and Families":125.00, "City Development":56.67},
			"2020-03": {"total":100.83, "Children and Families":100.83},
			"2020-08": {"total":150.00, "Children and Families":150.00},
			"2020-09": {"total":2.08, "Children and Families":2.08}
		}
	},
	"4315": {
		"name": "Arts And Minds Network",
		"total": 1800,
		"monthly": {
			"2011-07": {"total":1800.00, "City Development":1800.00}
		}
	},
	"4316": {
		"name": "Arts Cafe Bar",
		"total": 121.07,
		"monthly": {
			"2015-09": {"total":92.90, "Childrens Services":92.90},
			"2017-10": {"total":28.17, "City Development":28.17}
		}
	},
	"4317": {
		"name": "Arts Contact Ltd",
		"total": 640,
		"monthly": {
			"2018-08": {"total":180.00, "City Development":180.00},
			"2018-09": {"total":280.00, "City Development":280.00},
			"2019-11": {"total":180.00, "City Development":180.00}
		}
	},
	"4318": {
		"name": "Arts Development Uk",
		"total": 835,
		"monthly": {
			"2014-03": {"total":175.00, "City Development":175.00},
			"2014-06": {"total":125.00, "City Development":125.00},
			"2015-04": {"total":175.00, "City Development":175.00},
			"2016-03": {"total":180.00, "City Development":180.00},
			"2017-04": {"total":180.00, "City Development":180.00}
		}
	},
	"4319": {
		"name": "Arts Intelligence Ltd",
		"total": 3276,
		"monthly": {
			"2018-02": {"total":450.00, "City Development":450.00},
			"2018-08": {"total":476.00, "City Development":476.00},
			"2019-01": {"total":450.00, "City Development":450.00},
			"2019-02": {"total":595.00, "City Development":595.00},
			"2019-08": {"total":855.00, "Resources and Housing":855.00},
			"2021-05": {"total":450.00, "City Development":450.00}
		}
	},
	"4320": {
		"name": "Arts Learning Consortium",
		"total": 101.07,
		"monthly": {
			"2015-06": {"total":90.00, "City Development":90.00},
			"2015-08": {"total":11.07, "City Development":11.07}
		}
	},
	"4321": {
		"name": "Arts Leeds Ltd",
		"total": 65.67,
		"monthly": {
			"2019-08": {"total":31.67, "City Development":31.67},
			"2019-11": {"total":34.00, "City Development":34.00}
		}
	},
	"4322": {
		"name": "Arts Marketing Ass",
		"total": 1845,
		"monthly": {
			"2021-10": {"total":240.00, "City Development":240.00},
			"2022-01": {"total":420.00, "City Development":420.00},
			"2022-04": {"total":1185.00, "City Development":1185.00}
		}
	},
	"4323": {
		"name": "Arts Marketing Associa",
		"total": 408,
		"monthly": {
			"2019-08": {"total":408.00, "City Development":408.00}
		}
	},
	"4324": {
		"name": "Arts Marketing Association",
		"total": 5116,
		"monthly": {
			"2011-07": {"total":423.00, "City Development":423.00},
			"2016-02": {"total":566.00, "City Development":566.00},
			"2016-05": {"total":50.00, "City Development":50.00},
			"2017-01": {"total":408.00, "City Development":408.00},
			"2018-01": {"total":45.00, "City Development":45.00},
			"2018-02": {"total":416.00, "City Development":416.00},
			"2018-03": {"total":158.00, "City Development":158.00},
			"2018-08": {"total":416.00, "City Development":416.00},
			"2018-10": {"total":491.00, "City Development":491.00},
			"2018-11": {"total":246.00, "City Development":246.00},
			"2019-01": {"total":55.00, "City Development":55.00},
			"2019-03": {"total":471.00, "City Development":471.00},
			"2019-07": {"total":420.00, "City Development":420.00},
			"2019-09": {"total":165.00, "City Development":165.00},
			"2019-11": {"total":366.00, "City Development":366.00},
			"2020-02": {"total":420.00, "City Development":420.00}
		}
	},
	"4325": {
		"name": "Arts Marketingasso",
		"total": 368,
		"monthly": {
			"2016-07": {"total":273.00, "City Development":273.00},
			"2016-09": {"total":95.00, "City Development":95.00}
		}
	},
	"4326": {
		"name": "Arts Media Contacts Ltd",
		"total": 450,
		"monthly": {
			"2019-01": {"total":450.00, "City Development":450.00}
		}
	},
	"4327": {
		"name": "Arts Professional",
		"total": 195,
		"monthly": {
			"2022-02": {"total":195.00, "City Development":195.00}
		}
	},
	"4328": {
		"name": "Arts Professional Media Ltd",
		"total": 950,
		"monthly": {
			"2021-11": {"total":450.00, "Resources and Housing":450.00},
			"2022-03": {"total":250.00, "City Development":250.00},
			"2022-07": {"total":250.00, "City Development":250.00}
		}
	},
	"4329": {
		"name": "Arts To Share",
		"total": 1250.17,
		"monthly": {
			"2015-06": {"total":300.00, "Strategic Accounts":300.00},
			"2015-07": {"total":950.17, "Strategic Accounts":950.17}
		}
	},
	"4330": {
		"name": "Arts To Share (Leeds)",
		"total": 3050,
		"monthly": {
			"2016-12": {"total":450.00, "Strategic Accounts":450.00},
			"2017-01": {"total":300.00, "Strategic Accounts":300.00},
			"2017-02": {"total":150.00, "Strategic Accounts":150.00},
			"2017-03": {"total":50.00, "Strategic Accounts":50.00},
			"2017-10": {"total":100.00, "Strategic Accounts":100.00},
			"2017-11": {"total":200.00, "Strategic Accounts":200.00},
			"2018-08": {"total":400.00, "Strategic Accounts":400.00},
			"2018-10": {"total":1000.00, "City Development":1000.00},
			"2019-09": {"total":300.00, "Strategic Accounts":300.00},
			"2019-10": {"total":100.00, "Strategic Accounts":100.00}
		}
	},
	"4331": {
		"name": "Arts Trinity Ltd",
		"total": 1600,
		"monthly": {
			"2012-07": {"total":600.00, "Strategic Accounts":600.00},
			"2013-05": {"total":1000.00, "City Development":1000.00}
		}
	},
	"4332": {
		"name": "Arts and Flowers Ltd",
		"total": 280.83,
		"monthly": {
			"2019-04": {"total":120.83, "Children and Families":120.83},
			"2020-06": {"total":100.00, "Children and Families":100.00},
			"2020-07": {"total":60.00, "Children and Families":60.00}
		}
	},
	"4333": {
		"name": "Artsbloc",
		"total": 250,
		"monthly": {
			"2022-02": {"total":250.00, "City Development":250.00}
		}
	},
	"4334": {
		"name": "Artsemergen",
		"total": 200,
		"monthly": {
			"2015-07": {"total":200.00, "City Development":200.00}
		}
	},
	"4335": {
		"name": "Artsjobsonline",
		"total": 630,
		"monthly": {
			"2021-05": {"total":150.00, "City Development":150.00},
			"2021-08": {"total":300.00, "City Development":300.00},
			"2021-10": {"total":180.00, "City Development":180.00}
		}
	},
	"4336": {
		"name": "Artsmix",
		"total": 11891,
		"monthly": {
			"2011-02": {"total":11891.00, "City Development":11891.00}
		}
	},
	"4337": {
		"name": "Artsprofessional",
		"total": 351,
		"monthly": {
			"2020-01": {"total":156.00, "City Development":156.00},
			"2021-04": {"total":195.00, "City Development":195.00}
		}
	},
	"4338": {
		"name": "Artswork",
		"total": 108.33,
		"monthly": {
			"2016-07": {"total":108.33, "City Development":108.33}
		}
	},
	"4339": {
		"name": "Arttechspace Ltd",
		"total": 15,
		"monthly": {
			"2021-07": {"total":15.00, "Resources":15.00}
		}
	},
	"4340": {
		"name": "Arturas Indriunas",
		"total": 2577.04,
		"monthly": {
			"2022-04": {"total":2577.04, "Communities Housing and Environment":2577.04}
		}
	},
	"4341": {
		"name": "Arturas Zajanckauskas",
		"total": 2124,
		"monthly": {
			"2022-02": {"total":1416.00, "City Development":1416.00},
			"2022-03": {"total":708.00, "City Development":708.00}
		}
	},
	"4342": {
		"name": "Artventurers West Leeds",
		"total": 150,
		"monthly": {
			"2020-03": {"total":150.00, "City Development":150.00}
		}
	},
	"4343": {
		"name": "Artway Ltd",
		"alternate-names": [
			"Artway Limited"
		],
		"total": 2229.43,
		"monthly": {
			"2017-10": {"total":746.08, "Communities and Environment":746.08},
			"2017-11": {"total":22.83, "Communities and Environment":22.83},
			"2018-02": {"total":208.98, "Communities and Environment":208.98},
			"2018-04": {"total":134.43, "Communities and Environment":134.43},
			"2018-05": {"total":38.45, "Communities and Environment":38.45},
			"2018-11": {"total":14.53, "Communities and Environment":14.53},
			"2018-12": {"total":343.03, "Communities and Environment":343.03},
			"2019-01": {"total":25.73, "Communities and Environment":25.73},
			"2019-06": {"total":105.20, "Communities and Environment":105.20},
			"2019-07": {"total":13.50, "Communities and Environment":13.50},
			"2019-09": {"total":282.08, "Communities and Environment":282.08},
			"2019-10": {"total":109.33, "Communities and Environment":109.33},
			"2022-01": {"total":73.14, "Communities Housing and Environment":73.14},
			"2022-02": {"total":112.12, "City Development":69.50, "Communities Housing and Environment":42.62}
		}
	},
	"4344": {
		"name": "Artway.Co.Uk",
		"total": 89.53,
		"monthly": {
			"2022-03": {"total":15.63, "Communities Housing and Environment":15.63},
			"2022-04": {"total":73.90, "Communities Housing and Environment":73.90}
		}
	},
	"4345": {
		"name": "Artworks Conservation",
		"total": 510,
		"monthly": {
			"2018-12": {"total":510.00, "City Development":510.00}
		}
	},
	"4346": {
		"name": "Artworks Creative Communities",
		"total": 5700,
		"monthly": {
			"2019-08": {"total":450.00, "City Development":450.00},
			"2020-03": {"total":450.00, "City Development":450.00},
			"2021-05": {"total":3800.00, "City Development":3800.00},
			"2021-08": {"total":1000.00, "City Development":1000.00}
		}
	},
	"4347": {
		"name": "Artz Academy",
		"total": 324.56,
		"monthly": {
			"2015-09": {"total":324.56, "City Development":324.56}
		}
	},
	"4348": {
		"name": "Arun Dc Elms",
		"total": 70,
		"monthly": {
			"2020-03": {"total":70.00, "Resources and Housing":70.00}
		}
	},
	"4349": {
		"name": "Arunas Kugauda",
		"total": 4700.85,
		"monthly": {
			"2013-11": {"total":656.05, "Central & Corporate":656.05},
			"2013-12": {"total":1042.70, "Central & Corporate":1042.70},
			"2014-02": {"total":371.05, "Central & Corporate":371.05},
			"2014-03": {"total":70.00, "Central & Corporate":70.00},
			"2014-04": {"total":60.50, "Central & Corporate":60.50},
			"2014-05": {"total":119.40, "Central & Corporate":119.40},
			"2014-06": {"total":82.25, "Central & Corporate":82.25},
			"2014-07": {"total":140.00, "Central & Corporate":140.00},
			"2014-08": {"total":140.50, "Central & Corporate":140.50},
			"2014-09": {"total":81.30, "Central & Corporate":81.30},
			"2014-10": {"total":121.75, "Central & Corporate":121.75},
			"2014-11": {"total":392.35, "Central & Corporate":392.35},
			"2014-12": {"total":512.90, "Central & Corporate":512.90},
			"2015-02": {"total":216.40, "Central & Corporate":216.40},
			"2015-03": {"total":105.35, "Central & Corporate":105.35},
			"2015-04": {"total":363.60, "Central & Corporate":363.60},
			"2015-05": {"total":179.75, "Central & Corporate":179.75},
			"2015-06": {"total":45.00, "Central & Corporate":45.00}
		}
	}
	}
}