{
	"range": ["2010-10","2021-04"],
	"data": {
	"43000": {
		"name": "Sp * Aftershokz",
		"total": 116.58,
		"monthly": {
			"2020-10": {"total":58.29, "Children and Families":58.29},
			"2020-11": {"total":58.29, "Children and Families":58.29}
		}
	},
	"43001": {
		"name": "Sp * Allcam",
		"total": 178.22,
		"monthly": {
			"2018-04": {"total":61.62, "City Development":61.62},
			"2019-02": {"total":116.60, "City Development":116.60}
		}
	},
	"43002": {
		"name": "Sp * Allcolour Env Ltd",
		"total": 285.55,
		"monthly": {
			"2019-11": {"total":285.55, "Strategic Landlord":285.55}
		}
	},
	"43003": {
		"name": "Sp * Allergy Best Buys",
		"total": 15.9,
		"monthly": {
			"2020-05": {"total":15.90, "Children and Families":15.90}
		}
	},
	"43004": {
		"name": "Sp * Angel & Dove",
		"total": 36.65,
		"monthly": {
			"2020-10": {"total":36.65, "Resources and Housing":36.65}
		}
	},
	"43005": {
		"name": "Sp * Anti-Worlds",
		"total": 14.58,
		"monthly": {
			"2020-08": {"total":14.58, "City Development":14.58}
		}
	},
	"43006": {
		"name": "Sp * Artdiscount",
		"total": 518.8,
		"monthly": {
			"2019-06": {"total":39.46, "City Development":39.46},
			"2020-08": {"total":456.71, "Children and Families":456.71},
			"2020-12": {"total":22.63, "City Development":22.63}
		}
	},
	"43007": {
		"name": "Sp * B Malone",
		"total": 187.5,
		"monthly": {
			"2020-01": {"total":187.50, "Children and Families":187.50}
		}
	},
	"43008": {
		"name": "Sp * Batela Uk",
		"total": 57.6,
		"monthly": {
			"2019-03": {"total":57.60, "City Development":57.60}
		}
	},
	"43009": {
		"name": "Sp * Bath Publishing L",
		"total": 89.75,
		"monthly": {
			"2018-10": {"total":36.25, "Resources and Housing":36.25},
			"2019-07": {"total":53.50, "Resources and Housing":53.50}
		}
	},
	"43010": {
		"name": "Sp * Baylanguagebooks",
		"total": 44.01,
		"monthly": {
			"2019-04": {"total":14.67, "Children and Families":14.67},
			"2019-05": {"total":29.34, "Children and Families":29.34}
		}
	},
	"43011": {
		"name": "Sp * Bbco Headwear",
		"total": 34.03,
		"monthly": {
			"2019-11": {"total":34.03, "City Development":34.03}
		}
	},
	"43012": {
		"name": "Sp * Beco Uk",
		"total": 208.34,
		"monthly": {
			"2020-04": {"total":208.34, "Children and Families":208.34}
		}
	},
	"43013": {
		"name": "Sp * Bedroomking",
		"total": 499.99,
		"monthly": {
			"2021-01": {"total":499.99, "Children and Families":499.99}
		}
	},
	"43014": {
		"name": "Sp * Best Gym Equip",
		"total": 86.25,
		"monthly": {
			"2020-01": {"total":86.25, "City Development":86.25}
		}
	},
	"43015": {
		"name": "Sp * Bouncepad Hq",
		"total": 520,
		"monthly": {
			"2019-10": {"total":30.00, "City Development":30.00},
			"2019-11": {"total":245.00, "City Development":245.00},
			"2020-01": {"total":245.00, "City Development":245.00}
		}
	},
	"43016": {
		"name": "Sp * Browns Pet Range",
		"total": 60.97,
		"monthly": {
			"2020-04": {"total":60.97, "Communities and Environment":60.97}
		}
	},
	"43017": {
		"name": "Sp * Bunting Warehouse",
		"total": 424.5,
		"monthly": {
			"2019-06": {"total":424.50, "Resources and Housing":424.50}
		}
	},
	"43018": {
		"name": "Sp * Butlersessentials",
		"total": 40.29,
		"monthly": {
			"2020-03": {"total":40.29, "Resources and Housing":40.29}
		}
	},
	"43019": {
		"name": "Sp * Cannons Uk",
		"total": 433.3,
		"monthly": {
			"2019-09": {"total":83.33, "City Development":83.33},
			"2020-02": {"total":349.97, "City Development":349.97}
		}
	},
	"43020": {
		"name": "Sp * Chamberlain Music",
		"total": 16.67,
		"monthly": {
			"2019-10": {"total":16.67, "Children and Families":16.67}
		}
	},
	"43021": {
		"name": "Sp * Cleaning Club",
		"total": 222.46,
		"monthly": {
			"2020-03": {"total":222.46, "Communities and Environment":222.46}
		}
	},
	"43022": {
		"name": "Sp * Coloursmayvary.Co",
		"total": 150,
		"monthly": {
			"2020-02": {"total":150.00, "Communities and Environment":150.00}
		}
	},
	"43023": {
		"name": "Sp * Conservation Reso",
		"total": 141.47,
		"monthly": {
			"2019-10": {"total":76.55, "City Development":76.55},
			"2020-09": {"total":5.83, "City Development":5.83},
			"2021-03": {"total":59.09, "City Development":59.09}
		}
	},
	"43024": {
		"name": "Sp * Cool Components",
		"total": 185.08,
		"monthly": {
			"2020-02": {"total":185.08, "Communities and Environment":185.08}
		}
	},
	"43025": {
		"name": "Sp * Cupsdirect Uk",
		"total": 82.85,
		"monthly": {
			"2019-12": {"total":82.85, "Adults and Health":82.85}
		}
	},
	"43026": {
		"name": "Sp * Daals",
		"total": 134.99,
		"monthly": {
			"2021-01": {"total":134.99, "Children and Families":134.99}
		}
	},
	"43027": {
		"name": "Sp * Datazonedirect",
		"total": 14.88,
		"monthly": {
			"2018-08": {"total":14.88, "Communities and Environment":14.88}
		}
	},
	"43028": {
		"name": "Sp * Delphis Eco Uk",
		"total": 5561.88,
		"monthly": {
			"2018-04": {"total":944.20, "Communities and Environment":944.20},
			"2018-06": {"total":293.25, "Communities and Environment":293.25},
			"2018-07": {"total":680.35, "Communities and Environment":680.35},
			"2018-10": {"total":368.77, "Communities and Environment":368.77},
			"2018-12": {"total":536.68, "Communities and Environment":536.68},
			"2019-02": {"total":653.27, "Communities and Environment":653.27},
			"2019-03": {"total":416.90, "Communities and Environment":416.90},
			"2019-04": {"total":235.80, "Communities and Environment":235.80},
			"2019-05": {"total":423.43, "Communities and Environment":423.43},
			"2019-07": {"total":845.39, "Communities and Environment":845.39},
			"2021-03": {"total":163.84, "Communities and Environment":163.84}
		}
	},
	"43029": {
		"name": "Sp * Divan Bed Wh",
		"total": 639.9,
		"monthly": {
			"2020-11": {"total":289.95, "Children and Families":289.95},
			"2021-01": {"total":349.95, "Children and Families":349.95}
		}
	},
	"43030": {
		"name": "Sp * Down Syndrome Edu",
		"total": 83.34,
		"monthly": {
			"2020-05": {"total":83.34, "Children and Families":83.34}
		}
	},
	"43031": {
		"name": "Sp * Duronic",
		"total": 981.61,
		"monthly": {
			"2020-11": {"total":59.99, "Communities and Environment":59.99},
			"2021-01": {"total":466.64, "Children and Families":116.66, "Communities and Environment":116.66, "Resources and Housing":233.32},
			"2021-02": {"total":346.65, "City Development":129.99, "Communities and Environment":216.66},
			"2021-03": {"total":108.33, "Resources and Housing":108.33}
		}
	},
	"43032": {
		"name": "Sp * Ecostardust",
		"total": 32.5,
		"monthly": {
			"2019-10": {"total":32.50, "City Development":32.50}
		}
	},
	"43033": {
		"name": "Sp * Ecotech Store",
		"total": 1368.82,
		"monthly": {
			"2020-03": {"total":1361.30, "Resources and Housing":1361.30},
			"2020-04": {"total":7.52, "Resources and Housing":7.52}
		}
	},
	"43034": {
		"name": "Sp * Eduzone Ltd",
		"total": 100,
		"monthly": {
			"2021-02": {"total":100.00, "Children and Families":100.00}
		}
	},
	"43035": {
		"name": "Sp * Energybulbs.Co.Uk",
		"total": 58.91,
		"monthly": {
			"2019-09": {"total":14.41, "City Development":14.41},
			"2020-10": {"total":44.50, "Children and Families":44.50}
		}
	},
	"43036": {
		"name": "Sp * Fennec & Darwin",
		"total": 28.55,
		"monthly": {
			"2021-02": {"total":28.55, "Children and Families":28.55}
		}
	},
	"43037": {
		"name": "Sp * First Mats Ltd",
		"total": 307.55,
		"monthly": {
			"2020-12": {"total":104.95, "Children and Families":104.95},
			"2021-01": {"total":202.60, "Communities and Environment":202.60}
		}
	},
	"43038": {
		"name": "Sp * Five Star Party",
		"total": 36.21,
		"monthly": {
			"2020-12": {"total":36.21, "Communities and Environment":36.21}
		}
	},
	"43039": {
		"name": "Sp * Focusgamesltd",
		"total": 759.22,
		"monthly": {
			"2018-10": {"total":519.34, "Adults and Health":519.34},
			"2019-01": {"total":115.32, "Adults and Health":115.32},
			"2019-07": {"total":124.56, "Adults and Health":124.56}
		}
	},
	"43040": {
		"name": "Sp * Fred Aldous",
		"total": 160.74,
		"monthly": {
			"2018-04": {"total":34.85, "Communities and Environment":34.85},
			"2018-11": {"total":37.84, "City Development":8.49, "Communities and Environment":29.35},
			"2019-01": {"total":23.96, "City Development":23.96},
			"2019-05": {"total":44.17, "City Development":44.17},
			"2020-02": {"total":5.00, "City Development":5.00},
			"2021-02": {"total":14.92, "City Development":14.92}
		}
	},
	"43041": {
		"name": "Sp * Furnitubes Int. L",
		"total": 700,
		"monthly": {
			"2020-11": {"total":700.00, "Communities and Environment":700.00}
		}
	},
	"43042": {
		"name": "Sp * Gatehouse Books",
		"total": 7000,
		"monthly": {
			"2021-03": {"total":7000.00, "Communities and Environment":7000.00}
		}
	},
	"43043": {
		"name": "Sp * Gin Etc By Kitche",
		"total": 310.8,
		"monthly": {
			"2020-10": {"total":310.80, "Communities and Environment":310.80}
		}
	},
	"43044": {
		"name": "Sp * Grangers",
		"total": 7.28,
		"monthly": {
			"2021-02": {"total":7.28, "Communities and Environment":7.28}
		}
	},
	"43045": {
		"name": "Sp * Graphicsdirect.Co",
		"total": 11.76,
		"monthly": {
			"2018-12": {"total":4.88, "City Development":4.88},
			"2019-01": {"total":6.88, "City Development":6.88}
		}
	},
	"43046": {
		"name": "Sp * Grass Warehouse",
		"total": 2582.83,
		"monthly": {
			"2020-04": {"total":1415.44, "Children and Families":1415.44},
			"2020-05": {"total":1138.62, "Children and Families":1138.62},
			"2020-11": {"total":28.77, "City Development":28.77}
		}
	},
	"43047": {
		"name": "Sp * Greatideas.Co.Uk",
		"total": 10.74,
		"monthly": {
			"2020-06": {"total":10.74, "Adults and Health":10.74}
		}
	},
	"43048": {
		"name": "Sp * Gs Workwear",
		"total": 21.63,
		"monthly": {
			"2020-10": {"total":21.63, "Strategic Landlord":21.63}
		}
	},
	"43049": {
		"name": "Sp * Guildford Marine",
		"total": 15.85,
		"monthly": {
			"2020-02": {"total":15.85, "City Development":15.85}
		}
	}
	}
}