{
	"range": ["2010-09","2018-10"],
	"data": {
	"250": {
		"name": "1078.98",
		"total": 1078.98,
		"monthly": {
			"2018-05": {"total":1078.98, "Adults, Health and Social Care (obsolete)":0.00}
		}
	},
	"251": {
		"name": "10787.20",
		"total": 10787.2,
		"monthly": {
			"2018-08": {"total":10787.20, "Adults, Health and Social Care (obsolete)":0.00}
		}
	},
	"252": {
		"name": "10790.00",
		"total": 10790,
		"monthly": {
			"2018-05": {"total":10790.00, "Economy and Environment (obsolete)":10790.00}
		}
	},
	"253": {
		"name": "10796.04",
		"total": 10796.04,
		"monthly": {
			"2018-06": {"total":10796.04, "Adults, Health and Social Care (obsolete)":0.00}
		}
	},
	"254": {
		"name": "108.00",
		"total": 540,
		"monthly": {
			"2018-04": {"total":108.00, "Economy and Environment (obsolete)":108.00},
			"2018-05": {"total":108.00, "Communities & Service Support (obsolete)":108.00},
			"2018-08": {"total":216.00, "Communities & Service Support (obsolete)":108.00, "Children and Young People (obsolete)":108.00},
			"2018-10": {"total":108.00, "Communities & Service Support (obsolete)":108.00}
		}
	},
	"255": {
		"name": "108.29",
		"total": 108.29,
		"monthly": {
			"2018-04": {"total":108.29, "Communities & Service Support (obsolete)":108.29}
		}
	},
	"256": {
		"name": "108.35",
		"total": 108.35,
		"monthly": {
			"2018-08": {"total":108.35, "Economy and Environment (obsolete)":108.35}
		}
	},
	"257": {
		"name": "108.40",
		"total": 108.4,
		"monthly": {
			"2018-04": {"total":108.40, "Communities & Service Support (obsolete)":108.40}
		}
	},
	"258": {
		"name": "1080.00",
		"total": 10800,
		"monthly": {
			"2018-03": {"total":1080.00, "Economy and Environment (obsolete)":1080.00},
			"2018-04": {"total":1080.00, "Communities & Service Support (obsolete)":1080.00},
			"2018-05": {"total":1080.00, "Children and Young People (obsolete)":1080.00},
			"2018-06": {"total":2160.00, "Communities & Service Support (obsolete)":2160.00},
			"2018-08": {"total":3240.00, "Adults, Health and Social Care (obsolete)":0.00, "Communities & Service Support (obsolete)":2160.00},
			"2018-09": {"total":2160.00, "Communities & Service Support (obsolete)":1080.00, "Adults, Health and Social Care (obsolete)":0.00}
		}
	},
	"259": {
		"name": "1080.38",
		"total": 2160.76,
		"monthly": {
			"2018-05": {"total":1080.38, "Deputy Chief Executive (obsolete)":1080.38},
			"2018-08": {"total":1080.38, "Deputy Chief Executive (obsolete)":1080.38}
		}
	},
	"260": {
		"name": "10800.00",
		"total": 10800,
		"monthly": {
			"2018-04": {"total":10800.00, "Children and Young People (obsolete)":10800.00}
		}
	},
	"261": {
		"name": "10801.44",
		"total": 21602.88,
		"monthly": {
			"2018-04": {"total":10801.44, "Children and Young People (obsolete)":10801.44},
			"2018-05": {"total":10801.44, "Children and Young People (obsolete)":10801.44}
		}
	},
	"262": {
		"name": "108032.00",
		"total": 108032,
		"monthly": {
			"2018-07": {"total":108032.00, "Economy and Environment (obsolete)":108032.00}
		}
	},
	"263": {
		"name": "108045.17",
		"total": 108045.17,
		"monthly": {
			"2018-05": {"total":108045.17, "Children and Young People (obsolete)":108045.17}
		}
	},
	"264": {
		"name": "1081.86",
		"total": 1081.86,
		"monthly": {
			"2018-04": {"total":1081.86, "Adults, Health and Social Care (obsolete)":0.00}
		}
	},
	"265": {
		"name": "10811.00",
		"total": 21622,
		"monthly": {
			"2018-03": {"total":10811.00, "Adults, Health and Social Care (obsolete)":0.00},
			"2018-06": {"total":10811.00, "Adults, Health and Social Care (obsolete)":0.00}
		}
	},
	"266": {
		"name": "10826.56",
		"total": 10826.56,
		"monthly": {
			"2018-10": {"total":10826.56, "Adult Services and Wellbeing":10826.56}
		}
	},
	"267": {
		"name": "1083.87",
		"total": 1083.87,
		"monthly": {
			"2018-04": {"total":1083.87, "Communities & Service Support (obsolete)":1083.87}
		}
	},
	"268": {
		"name": "1085.00",
		"total": 2170,
		"monthly": {
			"2018-04": {"total":1085.00, "Economy and Environment (obsolete)":1085.00},
			"2018-09": {"total":1085.00, "Adults, Health and Social Care (obsolete)":0.00}
		}
	},
	"269": {
		"name": "1085.66",
		"total": 3256.98,
		"monthly": {
			"2018-03": {"total":1085.66, "Adults, Health and Social Care (obsolete)":0.00},
			"2018-04": {"total":1085.66, "Adults, Health and Social Care (obsolete)":0.00},
			"2018-08": {"total":1085.66, "Adults, Health and Social Care (obsolete)":0.00}
		}
	},
	"270": {
		"name": "1085.96",
		"total": 1085.96,
		"monthly": {
			"2018-06": {"total":1085.96, "Economy and Environment (obsolete)":1085.96}
		}
	},
	"271": {
		"name": "10857.60",
		"total": 21715.2,
		"monthly": {
			"2018-05": {"total":21715.20, "Adults, Health and Social Care (obsolete)":0.00}
		}
	},
	"272": {
		"name": "1086.75",
		"total": 2173.5,
		"monthly": {
			"2018-04": {"total":2173.50, "Adults, Health and Social Care (obsolete)":0.00}
		}
	},
	"273": {
		"name": "10863.84",
		"total": 10863.84,
		"monthly": {
			"2018-09": {"total":10863.84, "Economy and Environment (obsolete)":10863.84}
		}
	},
	"274": {
		"name": "1087.30",
		"total": 1087.3,
		"monthly": {
			"2018-05": {"total":1087.30, "Children and Young People (obsolete)":1087.30}
		}
	},
	"275": {
		"name": "1088.35",
		"total": 1088.35,
		"monthly": {
			"2018-05": {"total":1088.35, "Economy and Environment (obsolete)":1088.35}
		}
	},
	"276": {
		"name": "10880.88",
		"total": 10880.88,
		"monthly": {
			"2018-08": {"total":10880.88, "Adults, Health and Social Care (obsolete)":0.00}
		}
	},
	"277": {
		"name": "1089.00",
		"total": 1089,
		"monthly": {
			"2018-04": {"total":1089.00, "Children and Young People (obsolete)":1089.00}
		}
	},
	"278": {
		"name": "1089.20",
		"total": 1089.2,
		"monthly": {
			"2018-07": {"total":1089.20, "Adults, Health and Social Care (obsolete)":0.00}
		}
	},
	"279": {
		"name": "109.00",
		"total": 109,
		"monthly": {
			"2018-09": {"total":109.00, "Chief Executive's Office (obsolete)":109.00}
		}
	},
	"280": {
		"name": "1090.00",
		"total": 2180,
		"monthly": {
			"2018-07": {"total":2180.00, "Economy and Environment (obsolete)":1090.00, "Adults, Health and Social Care (obsolete)":0.00}
		}
	},
	"281": {
		"name": "1090.40",
		"total": 1090.4,
		"monthly": {
			"2018-07": {"total":1090.40, "Economy and Environment (obsolete)":1090.40}
		}
	},
	"282": {
		"name": "1091.43",
		"total": 1091.43,
		"monthly": {
			"2018-05": {"total":1091.43, "Adults, Health and Social Care (obsolete)":0.00}
		}
	},
	"283": {
		"name": "1091.80",
		"total": 2183.6,
		"monthly": {
			"2018-02": {"total":1091.80, "Adults, Health and Social Care":0.00},
			"2018-03": {"total":1091.80, "Adults, Health and Social Care (obsolete)":0.00}
		}
	},
	"284": {
		"name": "1095.09",
		"total": 1095.09,
		"monthly": {
			"2018-06": {"total":1095.09, "Communities & Service Support (obsolete)":1095.09}
		}
	},
	"285": {
		"name": "1095.80",
		"total": 1095.8,
		"monthly": {
			"2018-10": {"total":1095.80, "Adult Services and Wellbeing":1095.80}
		}
	},
	"286": {
		"name": "1095.84",
		"total": 2191.68,
		"monthly": {
			"2018-03": {"total":1095.84, "Adults, Health and Social Care (obsolete)":0.00},
			"2018-04": {"total":1095.84, "Adults, Health and Social Care (obsolete)":0.00}
		}
	},
	"287": {
		"name": "10952.00",
		"total": 10952,
		"monthly": {
			"2018-04": {"total":10952.00, "Children and Young People (obsolete)":10952.00}
		}
	},
	"288": {
		"name": "10964.01",
		"total": 10964.01,
		"monthly": {
			"2018-08": {"total":10964.01, "Adults, Health and Social Care (obsolete)":0.00}
		}
	},
	"289": {
		"name": "10966.29",
		"total": 10966.29,
		"monthly": {
			"2018-04": {"total":10966.29, "Adults, Health and Social Care (obsolete)":0.00}
		}
	},
	"290": {
		"name": "1097.00",
		"total": 1097,
		"monthly": {
			"2018-07": {"total":1097.00, "Children and Young People (obsolete)":1097.00}
		}
	},
	"291": {
		"name": "1097.64",
		"total": 1097.64,
		"monthly": {
			"2018-02": {"total":1097.64, "Children and Young People":1097.64}
		}
	},
	"292": {
		"name": "1098.00",
		"total": 1098,
		"monthly": {
			"2018-03": {"total":1098.00, "Economy and Environment (obsolete)":1098.00}
		}
	},
	"293": {
		"name": "1098.06",
		"total": 7686.42,
		"monthly": {
			"2018-02": {"total":2196.12, "Children and Young People":2196.12},
			"2018-03": {"total":1098.06, "Chief Executive's Office (obsolete)":1098.06},
			"2018-04": {"total":4392.24, "Deputy Chief Executive (obsolete)":1098.06, "Children and Young People (obsolete)":3294.18}
		}
	},
	"294": {
		"name": "1099.13",
		"total": 1099.13,
		"monthly": {
			"2018-10": {"total":1099.13, "unknown":1099.13}
		}
	},
	"295": {
		"name": "1099.95",
		"total": 1099.95,
		"monthly": {
			"2018-03": {"total":1099.95, "Adults, Health and Social Care (obsolete)":0.00}
		}
	},
	"296": {
		"name": "1099.98",
		"total": 1099.98,
		"monthly": {
			"2018-05": {"total":1099.98, "Communities & Service Support (obsolete)":1099.98}
		}
	},
	"297": {
		"name": "11.00",
		"total": 11,
		"monthly": {
			"2018-05": {"total":11.00, "Communities & Service Support (obsolete)":11.00}
		}
	},
	"298": {
		"name": "11.07",
		"total": 11.07,
		"monthly": {
			"2018-10": {"total":11.07, "Communities & Service Support (obsolete)":11.07}
		}
	},
	"299": {
		"name": "11.19",
		"total": 22.38,
		"monthly": {
			"2018-03": {"total":11.19, "Children and Young People (obsolete)":11.19},
			"2018-04": {"total":11.19, "Children and Young People (obsolete)":11.19}
		}
	}
	}
}