{
	"range": ["2013-04","2020-12"],
	"data": {
	"11200": {
		"name": "JUNGHEIRICH U.K. LTD",
		"total": 11570.61,
		"monthly": {
			"2013-04": {"total":703.50, "Civil Engineering Construction Works":703.50},
			"2013-05": {"total":737.00, "Civil Engineering Construction Works":737.00},
			"2013-06": {"total":2157.11, "Civil Engineering Construction Works":770.50, "Equipment Hire & Rental":1386.61},
			"2013-07": {"total":670.00, "Civil Engineering Construction Works":670.00},
			"2013-08": {"total":770.50, "Civil Engineering Construction Works":770.50},
			"2013-09": {"total":737.00, "Civil Engineering Construction Works":737.00},
			"2013-10": {"total":703.50, "Civil Engineering Construction Works":703.50},
			"2013-11": {"total":770.50, "Civil Engineering Construction Works":770.50},
			"2013-12": {"total":703.50, "Civil Engineering Construction Works":703.50},
			"2014-01": {"total":737.00, "Civil Engineering Construction Works":737.00},
			"2014-02": {"total":770.50, "Civil Engineering Construction Works":770.50},
			"2014-03": {"total":670.00, "Civil Engineering Construction Works":670.00},
			"2014-04": {"total":703.50, "LUL NOMINEE SSL LIMITED":703.50},
			"2014-06": {"total":737.00, "LUL NOMINEE SSL LIMITED":737.00}
		}
	},
	"11201": {
		"name": "JUNK ORCHESTRA LTD",
		"total": 5940,
		"monthly": {
			"2017-09": {"total":2970.00, "LONDON TRANSPORT MUSEUM":2970.00},
			"2017-10": {"total":2970.00, "LONDON TRANSPORT MUSEUM":2970.00}
		}
	},
	"11202": {
		"name": "JUPITER DISPLAY",
		"total": 11069,
		"monthly": {
			"2014-03": {"total":2995.00, "Printing":2995.00},
			"2014-04": {"total":7074.00, "LONDON UNDERGROUND LTD":2579.00, "TFL CORPORATE":4495.00},
			"2014-08": {"total":1000.00, "LONDON UNDERGROUND LTD":1000.00}
		}
	},
	"11203": {
		"name": "JUPITER TAXI RENTALS",
		"total": 7000,
		"monthly": {
			"2020-08": {"total":7000.00, "SURFACE TRANSPORT CORP":7000.00}
		}
	},
	"11204": {
		"name": "JUPITER TAXI RENTALS LTD",
		"total": 7000,
		"monthly": {
			"2020-08": {"total":7000.00, "SURFACE TRANSPORT CORP":7000.00}
		}
	},
	"11205": {
		"name": "JURA CONSULTANTS LTD",
		"alternate-names": [
			"JURA CONSULTANTS LIMITED"
		],
		"total": 41065.5,
		"monthly": {
			"2019-08": {"total":13688.50, "LONDON TRANSPORT MUSEUM":13688.50},
			"2019-09": {"total":27377.00, "LONDON TRANSPORT MUSEUM":27377.00}
		}
	},
	"11206": {
		"name": "JURATE CLARKE",
		"total": 638.2,
		"monthly": {
			"2014-05": {"total":386.26, "LONDON UNDERGROUND LTD":386.26},
			"2016-04": {"total":251.94, "LONDON UNDERGROUND LTD":251.94}
		}
	},
	"11207": {
		"name": "JUST EAT",
		"total": 271.87,
		"monthly": {
			"2015-02": {"total":15.69, "LONDON TRANSPORT MUSEUM":15.69},
			"2019-10": {"total":256.18, "LONDON UNDERGROUND LTD":256.18}
		}
	},
	"11208": {
		"name": "JUST GB",
		"total": 95.99,
		"monthly": {
			"2017-02": {"total":95.99, "TFL CORPORATE":95.99}
		}
	},
	"11209": {
		"name": "JUST HOSPITALITY LTD",
		"total": 372.5,
		"monthly": {
			"2015-11": {"total":372.50, "LONDON UNDERGROUND LTD":372.50}
		}
	},
	"11210": {
		"name": "JUST IT TRAINING LTD",
		"total": 4080,
		"monthly": {
			"2013-04": {"total":4080.00, "Staff Training":4080.00}
		}
	},
	"11211": {
		"name": "JUST JOE BUSINESS CATERERS",
		"total": 5627.7,
		"monthly": {
			"2013-11": {"total":772.50, "Caterers Service Charges":772.50},
			"2014-04": {"total":800.00, "LONDON UNDERGROUND LTD":800.00},
			"2014-09": {"total":444.10, "LONDON UNDERGROUND LTD":444.10},
			"2015-02": {"total":271.50, "LONDON UNDERGROUND LTD":271.50},
			"2015-08": {"total":445.50, "PUBLIC CARRIAGE OFFICE":445.50},
			"2015-12": {"total":271.50, "LONDON UNDERGROUND LTD":271.50},
			"2016-01": {"total":684.40, "LONDON UNDERGROUND LTD":684.40},
			"2016-03": {"total":1629.00, "LONDON UNDERGROUND LTD":1629.00},
			"2016-12": {"total":309.20, "LONDON UNDERGROUND LTD":309.20}
		}
	},
	"11212": {
		"name": "JUST JOE CATERING",
		"total": 738.8,
		"monthly": {
			"2018-06": {"total":738.80, "TFL CORPORATE":738.80}
		}
	},
	"11213": {
		"name": "JUST KEYRINGS",
		"total": 370,
		"monthly": {
			"2014-11": {"total":370.00, "LONDON UNDERGROUND LTD":370.00}
		}
	},
	"11214": {
		"name": "JUST LANYARDS",
		"total": 387,
		"monthly": {
			"2019-10": {"total":387.00, "LONDON UNDERGROUND LTD":387.00}
		}
	},
	"11215": {
		"name": "JUST PROJECTOR LAMPS",
		"total": 92.83,
		"monthly": {
			"2018-02": {"total":92.83, "LONDON UNDERGROUND LTD":92.83}
		}
	},
	"11216": {
		"name": "JUST PROJECTORS",
		"total": 297.02,
		"monthly": {
			"2014-06": {"total":297.02, "LONDON UNDERGROUND LTD":297.02}
		}
	},
	"11217": {
		"name": "JUST RECRUIT GROUP LTD",
		"alternate-names": [
			"JUST RECRUIT GROUP LIMITED"
		],
		"total": 79023.37,
		"monthly": {
			"2019-01": {"total":31200.00, "TFL CORPORATE":31200.00},
			"2019-03": {"total":6529.39, "TFL CORPORATE":6529.39},
			"2019-04": {"total":4411.75, "TFL CORPORATE":4411.75},
			"2019-07": {"total":5470.57, "TFL CORPORATE":5470.57},
			"2019-12": {"total":6529.39, "TFL CORPORATE":6529.39},
			"2020-05": {"total":5294.10, "TFL CORPORATE":5294.10},
			"2020-06": {"total":5647.04, "TFL CORPORATE":5647.04},
			"2020-08": {"total":10588.20, "TFL CORPORATE":10588.20},
			"2020-10": {"total":3352.93, "TFL CORPORATE":3352.93}
		}
	},
	"11218": {
		"name": "JUST TAXIS",
		"total": 9000,
		"monthly": {
			"2019-06": {"total":9000.00, "SURFACE TRANSPORT CORP":9000.00}
		}
	},
	"11219": {
		"name": "JUST TAXIS SALES LTD",
		"total": 9000,
		"monthly": {
			"2019-05": {"total":9000.00, "SURFACE TRANSPORT CORP":9000.00}
		}
	},
	"11220": {
		"name": "JUSTIN BENNY BOWRY",
		"total": 17000,
		"monthly": {
			"2019-09": {"total":16000.00, "SURFACE TRANSPORT CORP":16000.00},
			"2020-02": {"total":1000.00, "SURFACE TRANSPORT CORP":1000.00}
		}
	},
	"11221": {
		"name": "JUSTIN GRAINGE PHOTOGRAPHY",
		"total": 16221,
		"monthly": {
			"2013-09": {"total":500.00, "Marketing Exhibitions & Events":500.00},
			"2014-01": {"total":278.00, "Marketing Exhibitions & Events":278.00},
			"2014-09": {"total":438.00, "TFL CORPORATE":438.00},
			"2014-10": {"total":595.00, "TFL CORPORATE":595.00},
			"2014-12": {"total":12853.00, "LONDON UNDERGROUND LTD":12250.00, "TFL CORPORATE":603.00},
			"2015-03": {"total":278.00, "TFL CORPORATE":278.00},
			"2015-05": {"total":603.00, "TFL CORPORATE":603.00},
			"2015-06": {"total":338.00, "TFL CORPORATE":338.00},
			"2015-07": {"total":338.00, "TFL CORPORATE":338.00}
		}
	},
	"11222": {
		"name": "JUSTPARK PARKING LTD",
		"alternate-names": [
			"JUSTPARK PARKING LIMITED"
		],
		"total": 4554.17,
		"monthly": {
			"2019-11": {"total":554.17, "LONDON UNDERGROUND LTD":554.17},
			"2020-02": {"total":4000.00, "LONDON UNDERGROUND LTD":4000.00}
		}
	},
	"11223": {
		"name": "JV BRIGHT TAXI PARTS",
		"total": 56000,
		"monthly": {
			"2019-06": {"total":9000.00, "SURFACE TRANSPORT CORP":9000.00},
			"2019-07": {"total":18000.00, "SURFACE TRANSPORT CORP":18000.00},
			"2019-08": {"total":1000.00, "SURFACE TRANSPORT CORP":1000.00},
			"2019-09": {"total":16000.00, "SURFACE TRANSPORT CORP":16000.00},
			"2019-11": {"total":10000.00, "SURFACE TRANSPORT CORP":10000.00},
			"2019-12": {"total":2000.00, "SURFACE TRANSPORT CORP":2000.00}
		}
	},
	"11224": {
		"name": "JV BRIGHT TAXIS PARTS JAMIE SMITH",
		"total": 1000,
		"monthly": {
			"2019-10": {"total":1000.00, "SURFACE TRANSPORT CORP":1000.00}
		}
	},
	"11225": {
		"name": "JW MARRIOTT - FRONT DESK",
		"total": 107.11,
		"monthly": {
			"2017-12": {"total":107.11, "LONDON UNDERGROUND LTD":107.11}
		}
	},
	"11226": {
		"name": "JW POLLEY",
		"total": 330,
		"monthly": {
			"2017-05": {"total":330.00, "LONDON TRANSPORT MUSEUM":330.00}
		}
	},
	"11227": {
		"name": "Jacobs U.K Ltd",
		"alternate-names": [
			"Jacobs U.K Limited"
		],
		"total": 300398.77,
		"monthly": {
			"2020-07": {"total":238183.35, "LONDON TRANSPORT PROPERTY":238183.35},
			"2020-08": {"total":62215.42, "LONDON UNDERGROUND LTD":43710.58, "TFL CORPORATE":18504.84}
		}
	},
	"11228": {
		"name": "James Fisher Testing Services Ltd",
		"total": 106982.74,
		"monthly": {
			"2020-08": {"total":106982.74, "LONDON UNDERGROUND LTD":106982.74}
		}
	},
	"11229": {
		"name": "Jendee Trading Co Ltd",
		"total": 1115,
		"monthly": {
			"2020-07": {"total":1115.00, "TFL CORPORATE":1115.00}
		}
	},
	"11230": {
		"name": "Jenny Grieve",
		"total": 775,
		"monthly": {
			"2020-07": {"total":350.00, "TFL CORPORATE":350.00},
			"2020-08": {"total":425.00, "TFL CORPORATE":425.00}
		}
	},
	"11231": {
		"name": "Jetway Associates Ltd",
		"total": 1912.5,
		"monthly": {
			"2020-07": {"total":972.50, "LONDON UNDERGROUND LTD":972.50},
			"2020-08": {"total":940.00, "LONDON UNDERGROUND LTD":940.00}
		}
	},
	"11232": {
		"name": "John Wilkinson & Son (Builders) Ltd",
		"total": 540,
		"monthly": {
			"2020-07": {"total":540.00, "SURFACE TRANSPORT CORP":540.00}
		}
	},
	"11233": {
		"name": "Jointing Technologies",
		"total": 9732.51,
		"monthly": {
			"2020-07": {"total":8283.16, "LUL NOMINEE SSL LIMITED":8283.16},
			"2020-08": {"total":1449.35, "LUL NOMINEE SSL LIMITED":1449.35}
		}
	},
	"11234": {
		"name": "Juan Lopez",
		"total": 2000,
		"monthly": {
			"2020-08": {"total":2000.00, "TFL CORPORATE":2000.00}
		}
	},
	"11235": {
		"name": "Julie Ball",
		"total": 500,
		"monthly": {
			"2020-07": {"total":500.00, "TFL CORPORATE":500.00}
		}
	},
	"11236": {
		"name": "Jungheinrich Financial Services Ltd",
		"total": 2260.08,
		"monthly": {
			"2020-08": {"total":2260.08, "LONDON UNDERGROUND LTD":2260.08}
		}
	},
	"11237": {
		"name": "K & A CATERER'S",
		"total": 1805,
		"monthly": {
			"2015-07": {"total":800.00, "TFL CORPORATE":800.00},
			"2016-07": {"total":1005.00, "SURFACE TRANSPORT CORP":1005.00}
		}
	},
	"11238": {
		"name": "K & B PATEL",
		"total": 1447.56,
		"monthly": {
			"2013-10": {"total":1447.56, "Transys Control - TTL":1447.56}
		}
	},
	"11239": {
		"name": "K & K PATEL",
		"total": 1029.1,
		"monthly": {
			"2020-09": {"total":1029.10, "TRANSPORT TRADING LTD":1029.10}
		}
	},
	"11240": {
		"name": "K & L GATES",
		"total": 7496076.23,
		"monthly": {
			"2013-04": {"total":47299.55, "Legal Fees":47299.55},
			"2013-05": {"total":25003.80, "Legal Fees":25003.80},
			"2013-06": {"total":21850.00, "Legal Fees":21850.00},
			"2013-07": {"total":94385.89, "Legal Fees":94385.89},
			"2013-08": {"total":26328.20, "Legal Fees":26328.20},
			"2013-09": {"total":36244.02, "Legal Fees":36244.02},
			"2013-10": {"total":147218.00, "Legal Fees":147218.00},
			"2013-11": {"total":126150.00, "Legal Fees":126150.00},
			"2013-12": {"total":132087.72, "Legal Fees":132087.72},
			"2014-01": {"total":4324.20, "Legal Fees":4324.20},
			"2014-02": {"total":31240.56, "Legal Fees":31240.56},
			"2014-04": {"total":233761.74, "LUL NOMINEE SSL LIMITED":233761.74},
			"2014-05": {"total":2770.00, "LONDON UNDERGROUND LTD":2770.00},
			"2014-06": {"total":-696.00, "TRANSPORT TRADING LTD":-696.00},
			"2014-09": {"total":209411.00, "LUL NOMINEE SSL LIMITED":209411.00},
			"2014-10": {"total":298.88, "LONDON UNDERGROUND LTD":298.88},
			"2014-11": {"total":4921.50, "TUBE LINES LTD":4921.50},
			"2014-12": {"total":138849.00, "LUL NOMINEE SSL LIMITED":138849.00},
			"2015-01": {"total":108748.50, "LUL NOMINEE SSL LIMITED":61798.00, "TUBE LINES LTD":46950.50},
			"2015-03": {"total":157391.00, "LUL NOMINEE SSL LIMITED":157391.00},
			"2015-04": {"total":0.00, "TUBELINES LTD":0.00},
			"2015-05": {"total":36725.00, "LUL NOMINEE BCV LIMITED":23475.00, "TUBELINES LTD":13250.00},
			"2015-06": {"total":356916.00, "LUL NOMINEE BCV LIMITED":23161.00, "LUL NOMINEE SSL LIMITED":333755.00},
			"2015-07": {"total":96424.50, "LUL NOMINEE SSL LIMITED":96424.50},
			"2015-08": {"total":1969.81, "LONDON UNDERGROUND LTD":1969.81},
			"2015-09": {"total":103024.00, "LUL NOMINEE BCV LIMITED":1684.50, "LUL NOMINEE SSL LIMITED":101339.50},
			"2015-11": {"total":58185.00, "LONDON UNDERGROUND LTD":9293.00, "LUL NOMINEE SSL LIMITED":48892.00},
			"2015-12": {"total":213034.50, "LUL NOMINEE BCV LIMITED":3536.50, "LUL NOMINEE SSL LIMITED":191240.00, "TUBELINES LTD":18258.00},
			"2016-01": {"total":6311.90, "LONDON UNDERGROUND LTD":6311.90},
			"2016-02": {"total":654504.00, "LONDON UNDERGROUND LTD":654504.00},
			"2016-03": {"total":73704.00, "TUBELINES LTD":73704.00},
			"2016-04": {"total":7420.50, "LONDON UNDERGROUND LTD":7420.50},
			"2016-05": {"total":115660.00, "RAIL FOR LONDON LIMITED":111733.00, "TUBELINES LTD":3927.00},
			"2016-06": {"total":124754.19, "LUL NOMINEE BCV LIMITED":7312.00, "RAIL FOR LONDON LIMITED":91057.19, "TFL CORPORATE":6357.00, "TUBELINES LTD":20028.00},
			"2016-07": {"total":249540.64, "RAIL FOR LONDON LIMITED":240640.64, "TFL CORPORATE":8900.00},
			"2016-08": {"total":401851.34, "RAIL FOR LONDON LIMITED":393761.34, "TFL CORPORATE":8090.00},
			"2016-09": {"total":17588.00, "TFL CORPORATE":17588.00},
			"2016-10": {"total":59711.06, "RAIL FOR LONDON LIMITED":53642.81, "TFL CORPORATE":6068.25},
			"2016-11": {"total":38310.00, "TUBELINES LTD":38310.00},
			"2016-12": {"total":126216.00, "RAIL FOR LONDON LIMITED":9505.00, "TFL CORPORATE":8900.00, "TUBELINES LTD":107811.00},
			"2017-01": {"total":7686.45, "TFL CORPORATE":7686.45},
			"2017-02": {"total":15363.10, "TFL CORPORATE":15363.10},
			"2017-03": {"total":71066.90, "LONDON UNDERGROUND LTD":52611.90, "TFL CORPORATE":18455.00},
			"2017-04": {"total":114326.23, "LONDON UNDERGROUND LTD":106587.10, "TFL CORPORATE":7739.13},
			"2017-05": {"total":13039.80, "TFL CORPORATE":13039.80},
			"2017-06": {"total":322236.65, "LONDON UNDERGROUND LTD":285540.60, "TFL CORPORATE":36696.05},
			"2017-07": {"total":16751.63, "TFL CORPORATE":7453.63, "TUBELINES LTD":9298.00},
			"2017-08": {"total":10413.60, "LONDON UNDERGROUND LTD":10413.60},
			"2017-10": {"total":30659.60, "LONDON UNDERGROUND LTD":27730.10, "TFL CORPORATE":2929.50},
			"2017-11": {"total":44250.91, "LONDON UNDERGROUND LTD":10805.20, "SURFACE TRANSPORT CORP":33445.71},
			"2018-01": {"total":112429.80, "LONDON UNDERGROUND LTD":111558.30, "LUL NOMINEE BCV LIMITED":871.50},
			"2018-02": {"total":100238.62, "LONDON UNDERGROUND LTD":91891.30, "SURFACE TRANSPORT CORP":8347.32},
			"2018-03": {"total":275592.40, "LONDON UNDERGROUND LTD":248616.70, "SURFACE TRANSPORT CORP":26975.70},
			"2018-04": {"total":652.05, "SURFACE TRANSPORT CORP":652.05},
			"2018-06": {"total":3175.20, "SURFACE TRANSPORT CORP":3175.20},
			"2018-07": {"total":357007.70, "LONDON UNDERGROUND LTD":354712.70, "SURFACE TRANSPORT CORP":2295.00},
			"2018-08": {"total":198961.65, "LONDON UNDERGROUND LTD":198961.65},
			"2018-10": {"total":62368.35, "LONDON UNDERGROUND LTD":62368.35},
			"2018-11": {"total":204913.50, "LONDON UNDERGROUND LTD":200625.00, "LUL NOMINEE SSL LIMITED":4288.50},
			"2018-12": {"total":194438.40, "LONDON UNDERGROUND LTD":188250.00, "LUL NOMINEE SSL LIMITED":6188.40},
			"2019-01": {"total":256742.80, "LONDON UNDERGROUND LTD":243928.40, "SURFACE TRANSPORT CORP":598.50, "TFL CORPORATE":12215.90},
			"2019-02": {"total":11577.50, "LUL NOMINEE SSL LIMITED":672.30, "SURFACE TRANSPORT CORP":578.70, "TFL CORPORATE":10326.50},
			"2019-03": {"total":234081.00, "LONDON UNDERGROUND LTD":234081.00},
			"2019-04": {"total":30845.81, "LONDON UNDERGROUND LTD":1735.25, "SURFACE TRANSPORT CORP":4705.80, "TFL CORPORATE":24404.76},
			"2019-06": {"total":19595.37, "TFL CORPORATE":19595.37},
			"2019-07": {"total":10620.05, "SURFACE TRANSPORT CORP":501.00, "TFL CORPORATE":10119.05},
			"2019-08": {"total":12500.00, "TFL CORPORATE":12500.00},
			"2019-09": {"total":6499.60, "LONDON UNDERGROUND LTD":2500.00, "TRANSPORT TRADING LTD":3999.60},
			"2019-10": {"total":17367.00, "SURFACE TRANSPORT CORP":17367.00},
			"2019-11": {"total":40266.06, "LUL NOMINEE SSL LIMITED":6320.00, "TFL CORPORATE":23160.16, "TRANSPORT TRADING LTD":10785.90},
			"2019-12": {"total":41877.00, "LUL NOMINEE SSL LIMITED":39586.50, "SURFACE TRANSPORT CORP":2290.50},
			"2020-01": {"total":14915.50, "LUL NOMINEE SSL LIMITED":14915.50},
			"2020-03": {"total":131511.00, "LUL NOMINEE SSL LIMITED":29458.00, "SURFACE TRANSPORT CORP":97053.00, "TRANSPORT TRADING LTD":5000.00},
			"2020-04": {"total":11896.50, "LUL NOMINEE SSL LIMITED":11896.50},
			"2020-05": {"total":175282.50, "LONDON RIVER SERVICES LTD":159934.50, "LUL NOMINEE SSL LIMITED":15348.00},
			"2020-06": {"total":35488.00, "LONDON RIVER SERVICES LTD":35488.00}
		}
	},
	"11241": {
		"name": "K & M KIRUPAGARAN",
		"total": 1897.59,
		"monthly": {
			"2020-11": {"total":1897.59, "TRANSPORT TRADING LTD":1897.59}
		}
	},
	"11242": {
		"name": "K & M STORES M N PATEL",
		"total": 1453.79,
		"monthly": {
			"2019-07": {"total":1453.79, "TRANSPORT TRADING LTD":1453.79}
		}
	},
	"11243": {
		"name": "K & N PATEL",
		"total": 830.73,
		"monthly": {
			"2018-08": {"total":830.73, "TRANSPORT TRADING LTD":830.73}
		}
	},
	"11244": {
		"name": "K & S @ LAW SOLICITORS",
		"total": 300,
		"monthly": {
			"2016-06": {"total":300.00, "LONDON UNDERGROUND LTD":300.00}
		}
	},
	"11245": {
		"name": "K & S GADHVI",
		"total": 399.98,
		"monthly": {
			"2019-11": {"total":399.98, "TRANSPORT TRADING LTD":399.98}
		}
	},
	"11246": {
		"name": "K C FOOD & WINE LTD MR KALENDER KAY",
		"total": 3504.9,
		"monthly": {
			"2018-03": {"total":3504.90, "TRANSPORT TRADING LTD":3504.90}
		}
	},
	"11247": {
		"name": "K CHAG T YOGIKRUPA",
		"total": 305.93,
		"monthly": {
			"2017-08": {"total":305.93, "TRANSPORT TRADING LTD":305.93}
		}
	},
	"11248": {
		"name": "K COLLEGE",
		"total": 5190,
		"monthly": {
			"2013-05": {"total":920.00, "Staff Training":920.00},
			"2013-06": {"total":1020.00, "Staff Training":1020.00},
			"2014-09": {"total":3250.00, "TFL CORPORATE":3250.00}
		}
	},
	"11249": {
		"name": "K D PAINE & ASSOCIATES LTD",
		"total": 71000,
		"monthly": {
			"2017-10": {"total":71000.00, "LONDON UNDERGROUND LTD":71000.00}
		}
	}
	}
}